<hexya>
    <data>

        <view id="account_cash_box_in_form" model="CashBoxIn">
            <form string="Put Money In">
                <separator string="Fill in this form if you put money in the cash register:" colspan="4"/>
                <group>
                    <field name="name" class="oe_inline"/>
                    <field name="amount" class="oe_inline"/>
                </group>
                <footer>
                    <button name="run" string="Put Money In" type="object" class="btn-primary"/>
                    <button special="cancel" string="Cancel" class="btn-default"/>
                </footer>
            </form>
        </view>

        <view id="account_cash_box_out_form" model="CashBoxOut">
            <form string="Take Money Out">
                <separator string="Describe why you take money from the cash register:"/>
                <group>
                    <field name="name" class="oe_inline"/>
                    <field name="amount" class="oe_inline"/>
                </group>
                <footer>
                    <button name="run" string="Take Money Out" type="object" class="btn-primary"/>
                    <button class="btn-default" special="cancel" string="Cancel"/>
                </footer>
            </form>
        </view>

        <action id="account_action_cash_box_in" name="Put Money In" model="CashBoxIn" src_model="AccountBankStatement"
                view_mode="form" target="new"/>

        <action id="account_action_cash_box_out" name="Take Money Out" model="CashBoxOut"
                src_model="AccountBankStatement" view_mode="form" target="new"/>

    </data>
</hexya>
